{
  "Mecanica": {
    "Materia Prima": [
      {
        "item": 1,
        "codigo": null,
        "denominacion": "Chapa SAE 1010, corte y plegado",
        "unidad": "Kg",
        "coeficiente": 1.0,
        "costo_fob": 3.45,
        "costo_fabrica": 3.45,
        "fecha": "2025-10-30 00:00:00"
      },
      {
        "item": 2,
        "codigo": null,
        "denominacion": "Chapa prezincada, corte y plegado",
        "unidad": "Kg",
        "coeficiente": 1.0,
        "costo_fob": 3.72,
        "costo_fabrica": 3.72,
        "fecha": "2025-10-30 00:00:00"
      },
      {
        "item": 3,
        "codigo": null,
        "denominacion": "Chapa AISI 304, corte y plegado",
        "unidad": "Kg",
        "coeficiente": 1.0,
        "costo_fob": 5.8,
        "costo_fabrica": 5.8,
        "fecha": "2025-10-30 00:00:00"
      },
      {
        "item": 4,
        "codigo": null,
        "denominacion": "Chapa AISI 430, corte y plegado",
        "unidad": "Kg",
        "coeficiente": 1.0,
        "costo_fob": 4.4,
        "costo_fabrica": 4.4,
        "fecha": "2025-10-30 00:00:00"
      },
      {
        "item": 5,
        "codigo": null,
        "denominacion": "Barra masiza SAE 1010",
        "unidad": "Kg",
        "coeficiente": 1.0,
        "costo_fob": 1.5,
        "costo_fabrica": 1.5,
        "fecha": "2025-10-30 00:00:00"
      },
      {
        "item": 6,
        "codigo": null,
        "denominacion": "Barra masiza SAE 4140",
        "unidad": "Kg",
        "coeficiente": 1.0,
        "costo_fob": 14.3,
        "costo_fabrica": 14.3,
        "fecha": "2025-10-30 00:00:00"
      },
      {
        "item": 7,
        "codigo": null,
        "denominacion": "Vidrio Laminado 3+3",
        "unidad": "M²",
        "coeficiente": 1.0,
        "costo_fob": 87.0,
        "costo_fabrica": 87.0,
        "fecha": "2025-10-30 00:00:00"
      },
      {
        "item": 8,
        "codigo": null,
        "denominacion": "Vidrio Templado 6mm",
        "unidad": "M²",
        "coeficiente": 1.0,
        "costo_fob": 105.8,
        "costo_fabrica": 105.8,
        "fecha": "2025-10-30 00:00:00"
      },
      {
        "item": 9,
        "codigo": null,
        "denominacion": "Vidrio Templado 10mm",
        "unidad": "M²",
        "coeficiente": 1.0,
        "costo_fob": 120.0,
        "costo_fabrica": 120.0,
        "fecha": "2025-10-30 00:00:00"
      },
      {
        "item": 10,
        "codigo": null,
        "denominacion": "Caño Inoxidable AISI 304 Ø38,1 x 1,5mm",
        "unidad": "Metro",
        "coeficiente": 1.0,
        "costo_fob": 8.43,
        "costo_fabrica": 8.43,
        "fecha": "2025-10-30 00:00:00"
      },
      {
        "item": 11,
        "codigo": null,
        "denominacion": "Caño Inoxidable AISI 304 Ø50,8 x 1mm",
        "unidad": "Metro",
        "coeficiente": 1.0,
        "costo_fob": 8.0,
        "costo_fabrica": 8.0,
        "fecha": "2025-10-30 00:00:00"
      },
      {
        "item": 12,
        "codigo": null,
        "denominacion": "Caño Inoxidable AISI 304 Ø31,75 x 1,5mm",
        "unidad": "Metro",
        "coeficiente": 1.0,
        "costo_fob": 7.12,
        "costo_fabrica": 7.12,
        "fecha": "2025-10-30 00:00:00"
      },
      {
        "item": 13,
        "codigo": null,
        "denominacion": "Caño estructural cuadrado 50x50x1,5mm Inoxidable AISI 304",
        "unidad": "Metro",
        "coeficiente": 1.0,
        "costo_fob": 14.2,
        "costo_fabrica": 14.2,
        "fecha": "2025-10-30 00:00:00"
      },
      {
        "item": 14,
        "codigo": null,
        "denominacion": "Caño Inoxidable AISI 304 Ø25,4 x 0,8mm",
        "unidad": "Metro",
        "coeficiente": 1.0,
        "costo_fob": 3.55,
        "costo_fabrica": 3.55,
        "fecha": "2025-10-30 00:00:00"
      },
      {
        "item": 15,
        "codigo": null,
        "denominacion": "Caño Inoxidable AISI 304 Ø25,4 x 1,6mm",
        "unidad": "Metro",
        "coeficiente": 1.0,
        "costo_fob": 4.0,
        "costo_fabrica": 4.0,
        "fecha": "2025-10-30 00:00:00"
      }
    ],
    "Mano de obra": [
      {
        "item": 16,
        "codigo": null,
        "denominacion": "Pintura",
        "unidad": "M²",
        "coeficiente": 1.0,
        "costo_fob": 15.0,
        "costo_fabrica": 15.0,
        "fecha": "2025-10-30 00:00:00"
      },
      {
        "item": 17,
        "codigo": null,
        "denominacion": "Pintura piezas plasticas",
        "unidad": "Cm²",
        "coeficiente": 1.0,
        "costo_fob": 0.5,
        "costo_fabrica": 0.5,
        "fecha": "2025-10-30 00:00:00"
      },
      {
        "item": 18,
        "codigo": null,
        "denominacion": "Soldar y Pulir",
        "unidad": "hora",
        "coeficiente": 1.0,
        "costo_fob": 15.0,
        "costo_fabrica": 15.0,
        "fecha": "2025-10-30 00:00:00"
      },
      {
        "item": 19,
        "codigo": null,
        "denominacion": "Mecanizado",
        "unidad": "hora",
        "coeficiente": 1.0,
        "costo_fob": 10.0,
        "costo_fabrica": 10.0,
        "fecha": "2025-10-30 00:00:00"
      },
      {
        "item": 20,
        "codigo": null,
        "denominacion": "Inyeccion de plastico",
        "unidad": "Gr",
        "coeficiente": 1.0,
        "costo_fob": 1.0,
        "costo_fabrica": 1.0,
        "fecha": "2025-10-30 00:00:00"
      },
      {
        "item": 21,
        "codigo": null,
        "denominacion": "Termoformado",
        "unidad": "Kg",
        "coeficiente": 1.0,
        "costo_fob": 25.0,
        "costo_fabrica": 25.0,
        "fecha": "2025-10-30 00:00:00"
      },
      {
        "item": 22,
        "codigo": null,
        "denominacion": "Zincado",
        "unidad": "Kg",
        "coeficiente": 1.0,
        "costo_fob": 2.5,
        "costo_fabrica": 2.5,
        "fecha": "2025-10-30 00:00:00"
      },
      {
        "item": 23,
        "codigo": null,
        "denominacion": "Armado Mecanico",
        "unidad": "hora",
        "coeficiente": 1.0,
        "costo_fob": 10.0,
        "costo_fabrica": 10.0,
        "fecha": "2025-10-30 00:00:00"
      }
    ],
    "Items comerciales": [
      {
        "item": 24,
        "codigo": null,
        "denominacion": "Minuteria Comun",
        "unidad": "Promedio",
        "coeficiente": 1.0,
        "costo_fob": 16.0,
        "costo_fabrica": 16.0,
        "fecha": "2025-10-30 00:00:00"
      },
      {
        "item": 25,
        "codigo": null,
        "denominacion": "Minuteria especial (Guias, rulemanes)",
        "unidad": "Promedio",
        "coeficiente": 1.0,
        "costo_fob": 16.0,
        "costo_fabrica": 16.0,
        "fecha": "2025-10-30 00:00:00"
      },
      {
        "item": 26,
        "codigo": null,
        "denominacion": "Cerradura de armario",
        "unidad": "Unidad",
        "coeficiente": 1.0,
        "costo_fob": 3.2,
        "costo_fabrica": 3.2,
        "fecha": "2025-10-30 00:00:00"
      },
      {
        "item": 27,
        "codigo": null,
        "denominacion": "Cerradura Merle",
        "unidad": "Unidad",
        "coeficiente": 1.0,
        "costo_fob": 15.0,
        "costo_fabrica": 15.0,
        "fecha": "2025-10-30 00:00:00"
      },
      {
        "item": 28,
        "codigo": null,
        "denominacion": "Correas dentadas",
        "unidad": "Unidad",
        "coeficiente": 1.0,
        "costo_fob": 11.2,
        "costo_fabrica": 11.2,
        "fecha": "2025-10-30 00:00:00"
      }
    ],
    "STD DCM": [
      {
        "item": 29,
        "codigo": null,
        "denominacion": "Mecanismo de Molinete MS",
        "unidad": "Unidad",
        "coeficiente": 1.0,
        "costo_fob": 500.0,
        "costo_fabrica": 500.0,
        "fecha": "2025-10-30 00:00:00"
      },
      {
        "item": 30,
        "codigo": null,
        "denominacion": "Mecanismo de Molinete MC",
        "unidad": "Unidad",
        "coeficiente": 1.0,
        "costo_fob": 400.0,
        "costo_fabrica": 400.0,
        "fecha": "2025-10-30 00:00:00"
      },
      {
        "item": 31,
        "codigo": null,
        "denominacion": "Soporte de lectores y aplique plastico",
        "unidad": "Unidad",
        "coeficiente": 1.0,
        "costo_fob": 15.0,
        "costo_fabrica": 15.0,
        "fecha": "2025-10-30 00:00:00"
      },
      {
        "item": 32,
        "codigo": null,
        "denominacion": "Bidireccional",
        "unidad": "Unidad",
        "coeficiente": 1.0,
        "costo_fob": 20.0,
        "costo_fabrica": 20.0,
        "fecha": "2025-10-30 00:00:00"
      },
      {
        "item": 33,
        "codigo": "BU500",
        "denominacion": "Buzón Motorizado",
        "unidad": "Unidad",
        "coeficiente": 1.0,
        "costo_fob": 220.0,
        "costo_fabrica": 220.0,
        "fecha": "2025-10-30 00:00:00"
      },
      {
        "item": 34,
        "codigo": null,
        "denominacion": "SAA Sistema antipanico Molinete MC juego de 3 brazos",
        "unidad": "Unidad",
        "coeficiente": 1.0,
        "costo_fob": 110.0,
        "costo_fabrica": 110.0,
        "fecha": "2025-10-30 00:00:00"
      }
    ]
  },
  "Electronica": {
    "Monitores": [
      {
        "item": 35,
        "codigo": "G104XVN01.0",
        "denominacion": "Monitor 10'' HD (Lixis)",
        "unidad": "Unidad",
        "coeficiente": 1.35,
        "costo_fob": 135.0,
        "costo_fabrica": 182.25,
        "fecha": "2025-10-30 00:00:00"
      },
      {
        "item": 36,
        "codigo": "G104SN03 V5 (230 nits)",
        "denominacion": "Monitor 10,4\" 800x600 (turneros)",
        "unidad": "Unidad",
        "coeficiente": 1.35,
        "costo_fob": 99.0,
        "costo_fabrica": 133.65,
        "fecha": "2025-10-30 00:00:00"
      },
      {
        "item": 37,
        "codigo": "G170ETN01.0",
        "denominacion": "Monitor 17''",
        "unidad": "Unidad",
        "coeficiente": 1.35,
        "costo_fob": 102.0,
        "costo_fabrica": 137.70000000000002,
        "fecha": "2025-10-30 00:00:00"
      },
      {
        "item": 38,
        "codigo": "G185XW01 V2",
        "denominacion": "Monitor 18.5''",
        "unidad": "Unidad",
        "coeficiente": 1.35,
        "costo_fob": 140.0,
        "costo_fabrica": 189.0,
        "fecha": "2025-10-30 00:00:00"
      },
      {
        "item": 39,
        "codigo": "M190ETN01.0",
        "denominacion": "Monitor 19''",
        "unidad": "Unidad",
        "coeficiente": 1.35,
        "costo_fob": 145.0,
        "costo_fabrica": 195.75,
        "fecha": "2025-10-30 00:00:00"
      },
      {
        "item": 40,
        "codigo": "G215HVN01",
        "denominacion": "Monitor 21,5''",
        "unidad": "Unidad",
        "coeficiente": 1.35,
        "costo_fob": 173.0,
        "costo_fabrica": 233.55,
        "fecha": "2025-10-30 00:00:00"
      },
      {
        "item": 41,
        "codigo": null,
        "denominacion": "Monitor 24''",
        "unidad": "Unidad",
        "coeficiente": 1.35,
        "costo_fob": 217.0,
        "costo_fabrica": 292.95000000000005,
        "fecha": "2025-10-30 00:00:00"
      },
      {
        "item": 42,
        "codigo": "P320HVN02.0",
        "denominacion": "Monitor 32''",
        "unidad": "Unidad",
        "coeficiente": 1.35,
        "costo_fob": 315.0,
        "costo_fabrica": 425.25,
        "fecha": "2025-10-30 00:00:00"
      },
      {
        "item": 43,
        "codigo": "P320HVN07.0",
        "denominacion": "Monitor 32'' Alta luminosidad",
        "unidad": "Unidad",
        "coeficiente": 1.35,
        "costo_fob": 550.0,
        "costo_fabrica": 742.5,
        "fecha": "2025-10-30 00:00:00"
      },
      {
        "item": 44,
        "codigo": null,
        "denominacion": "Monitor 42\"",
        "unidad": "Unidad",
        "coeficiente": 1.35,
        "costo_fob": 315.0,
        "costo_fabrica": 425.25,
        "fecha": "2025-10-30 00:00:00"
      },
      {
        "item": 45,
        "codigo": null,
        "denominacion": "Monitor 42\" Alta luminosidad",
        "unidad": "Unidad",
        "coeficiente": 1.35,
        "costo_fob": 550.0,
        "costo_fabrica": 742.5,
        "fecha": "2025-10-30 00:00:00"
      },
      {
        "item": 46,
        "codigo": "P550HVN09.1",
        "denominacion": "Monitor 55''",
        "unidad": "Unidad",
        "coeficiente": 1.35,
        "costo_fob": 535.0,
        "costo_fabrica": 722.25,
        "fecha": "2025-10-30 00:00:00"
      },
      {
        "item": 47,
        "codigo": "P550HVN06.4",
        "denominacion": "Monitor 55'' Alta luminosidad",
        "unidad": "Unidad",
        "coeficiente": 1.35,
        "costo_fob": 1325.0,
        "costo_fabrica": 1788.7500000000002,
        "fecha": "2025-10-30 00:00:00"
      },
      {
        "item": 48,
        "codigo": "LCD MP15001",
        "denominacion": "Monitor 5”",
        "unidad": "Unidad",
        "coeficiente": 1.35,
        "costo_fob": 26.8,
        "costo_fabrica": 36.18000000000001,
        "fecha": "2025-10-30 00:00:00"
      },
      {
        "item": 49,
        "codigo": null,
        "denominacion": "Display MEM",
        "unidad": "Unidad",
        "coeficiente": 1.0,
        "costo_fob": 48.8,
        "costo_fabrica": 48.8,
        "fecha": "2025-10-30 00:00:00"
      },
      {
        "item": 50,
        "codigo": null,
        "denominacion": "Conversor",
        "unidad": "Unidad",
        "coeficiente": 1.35,
        "costo_fob": 26.0,
        "costo_fabrica": 35.1,
        "fecha": "2025-10-30 00:00:00"
      }
    ],
    "Touch-screen": [
      {
        "item": 51,
        "codigo": "TS104A5B01",
        "denominacion": "Touch 10'' Resistivo con controlador",
        "unidad": "Unidad",
        "coeficiente": 1.35,
        "costo_fob": 25.0,
        "costo_fabrica": 33.75,
        "fecha": "2025-10-30 00:00:00"
      },
      {
        "item": 52,
        "codigo": "KTT502017",
        "denominacion": "Touch 17'' capacitivo sin controlador",
        "unidad": "Unidad",
        "coeficiente": 1.35,
        "costo_fob": 15.0,
        "costo_fabrica": 20.25,
        "fecha": "2025-10-30 00:00:00"
      },
      {
        "item": 53,
        "codigo": "KTT502318",
        "denominacion": "Touch 18.5'' capacitivo sin controlador",
        "unidad": "Unidad",
        "coeficiente": 1.35,
        "costo_fob": 15.0,
        "costo_fabrica": 20.25,
        "fecha": "2025-10-30 00:00:00"
      },
      {
        "item": 54,
        "codigo": "KTT502519",
        "denominacion": "Touch 19'' capacitivo sin controlador",
        "unidad": "Unidad",
        "coeficiente": 1.35,
        "costo_fob": 15.0,
        "costo_fabrica": 20.25,
        "fecha": "2025-10-30 00:00:00"
      },
      {
        "item": 55,
        "codigo": "KTT500521",
        "denominacion": "Touch 21.5'' capacitivo sin controlador",
        "unidad": "Unidad",
        "coeficiente": 1.35,
        "costo_fob": 15.0,
        "costo_fabrica": 20.25,
        "fecha": "2025-10-30 00:00:00"
      },
      {
        "item": 56,
        "codigo": "KTT504124",
        "denominacion": "Touch 24'' capacitivo sin controlador",
        "unidad": "Unidad",
        "coeficiente": 1.35,
        "costo_fob": 20.0,
        "costo_fabrica": 27.0,
        "fecha": "2025-10-30 00:00:00"
      },
      {
        "item": 57,
        "codigo": "32\"PCAP Touch Screen",
        "denominacion": "Touch 32'' capacitivo sin controlador",
        "unidad": "Unidad",
        "coeficiente": 1.35,
        "costo_fob": 40.0,
        "costo_fabrica": 54.0,
        "fecha": "2025-10-30 00:00:00"
      },
      {
        "item": 58,
        "codigo": "42\" PCAP",
        "denominacion": "Touch 42\" capacitivo sin controlador",
        "unidad": "Unidad",
        "coeficiente": 1.35,
        "costo_fob": 220.0,
        "costo_fabrica": 297.0,
        "fecha": "2025-10-30 00:00:00"
      },
      {
        "item": 59,
        "codigo": "55\" PCAP",
        "denominacion": "Touch 55\" capacitivo sin controlador",
        "unidad": "Unidad",
        "coeficiente": 1.35,
        "costo_fob": 265.0,
        "costo_fabrica": 357.75,
        "fecha": "2025-10-30 00:00:00"
      },
      {
        "item": 60,
        "codigo": "55” IR",
        "denominacion": "Touch 55” IR",
        "unidad": "Unidad",
        "coeficiente": 1.35,
        "costo_fob": 145.0,
        "costo_fabrica": 195.75,
        "fecha": "2025-10-30 00:00:00"
      },
      {
        "item": 61,
        "codigo": null,
        "denominacion": "Touch 10\" Capacitivo sin controlador",
        "unidad": "Unidad",
        "coeficiente": 1.35,
        "costo_fob": 18.0,
        "costo_fabrica": 24.3,
        "fecha": "2025-10-30 00:00:00"
      },
      {
        "item": 62,
        "codigo": "PCAP Touch screen controller",
        "denominacion": "Controlador touch",
        "unidad": "Unidad",
        "coeficiente": 1.35,
        "costo_fob": 32.0,
        "costo_fabrica": 43.2,
        "fecha": "2025-10-30 00:00:00"
      }
    ],
    "Motherboards": [
      {
        "item": 63,
        "codigo": "KEEX1760",
        "denominacion": "SR210",
        "unidad": "Unidad",
        "coeficiente": 1.35,
        "costo_fob": 200.0,
        "costo_fabrica": 270.0,
        "fecha": "2025-10-30 00:00:00"
      },
      {
        "item": 64,
        "codigo": null,
        "denominacion": "SR230",
        "unidad": "Unidad",
        "coeficiente": 1.35,
        "costo_fob": null,
        "costo_fabrica": 0.0,
        "fecha": "2025-10-30 00:00:00"
      },
      {
        "item": 65,
        "codigo": "QDS-8200",
        "denominacion": "Android Kontron",
        "unidad": "Unidad",
        "coeficiente": 1.35,
        "costo_fob": 160.0,
        "costo_fabrica": 216.0,
        "fecha": "2025-10-30 00:00:00"
      },
      {
        "item": 66,
        "codigo": "B3EXWLU0-011001T",
        "denominacion": "Lixis (PC Industrial - i3)",
        "unidad": "Unidad",
        "coeficiente": 1.35,
        "costo_fob": 420.0,
        "costo_fabrica": 567.0,
        "fecha": "2025-10-30 00:00:00"
      },
      {
        "item": 67,
        "codigo": "B3EXWLU0-031001T",
        "denominacion": "Lixis (PC Industrial - Celeron)",
        "unidad": "Unidad",
        "coeficiente": 1.35,
        "costo_fob": 290.0,
        "costo_fabrica": 391.5,
        "fecha": "2025-10-30 00:00:00"
      },
      {
        "item": 68,
        "codigo": null,
        "denominacion": "Disipador SR210",
        "unidad": "Unidad",
        "coeficiente": 1.35,
        "costo_fob": 20.0,
        "costo_fabrica": 27.0,
        "fecha": "2025-10-30 00:00:00"
      },
      {
        "item": 69,
        "codigo": "BPI-M2 Ultra",
        "denominacion": "Banana-Pi",
        "unidad": "Unidad",
        "coeficiente": 1.35,
        "costo_fob": 68.0,
        "costo_fabrica": 91.80000000000001,
        "fecha": "2025-10-30 00:00:00"
      },
      {
        "item": 70,
        "codigo": "Chino con monitor y touch",
        "denominacion": "ARM",
        "unidad": "Unidad",
        "coeficiente": 1.35,
        "costo_fob": 75.0,
        "costo_fabrica": 101.25,
        "fecha": "2025-10-30 00:00:00"
      },
      {
        "item": 71,
        "codigo": "Raspberry Pi 4 Model B 4Gb",
        "denominacion": "Raspberry Pi 4",
        "unidad": "Unidad",
        "coeficiente": 1.35,
        "costo_fob": 63.0,
        "costo_fabrica": 85.05000000000001,
        "fecha": "2025-10-30 00:00:00"
      },
      {
        "item": 72,
        "codigo": "ECX-WLU0  i5-8365UE w/ TPM",
        "denominacion": "3.5”-SBC-WLU-8365UE",
        "unidad": "Unidad",
        "coeficiente": 1.35,
        "costo_fob": 606.0,
        "costo_fabrica": 818.1,
        "fecha": "2025-10-30 00:00:00"
      },
      {
        "item": 73,
        "codigo": "ECX-WLU1  i3-8145UE w/ TPM",
        "denominacion": "3.5”-SBC-WLU-8145UE",
        "unidad": "Unidad",
        "coeficiente": 1.35,
        "costo_fob": 458.0,
        "costo_fabrica": 618.3000000000001,
        "fecha": "2025-10-30 00:00:00"
      },
      {
        "item": 74,
        "codigo": "ECX-WLU2  i7-8665UE w/ TPM",
        "denominacion": "3.5”-SBC-WLU-8665UE",
        "unidad": "Unidad",
        "coeficiente": 1.35,
        "costo_fob": 748.0,
        "costo_fabrica": 1009.8000000000001,
        "fecha": "2025-10-30 00:00:00"
      },
      {
        "item": 75,
        "codigo": "ECX-WLU3  Celeron 4305UE w/ TPM",
        "denominacion": "3.5”-SBC-WLU-4305UE",
        "unidad": "Unidad",
        "coeficiente": 1.35,
        "costo_fob": 317.0,
        "costo_fabrica": 427.95000000000005,
        "fecha": "2025-10-30 00:00:00"
      },
      {
        "item": 76,
        "codigo": "0H05XX000002270L Active cooler 63.5x50*13mm",
        "denominacion": "Active Cooler 3.5\"-SBC-WLU/TGL",
        "unidad": "Unidad",
        "coeficiente": 1.35,
        "costo_fob": 22.0,
        "costo_fabrica": 29.700000000000003,
        "fecha": "2025-10-30 00:00:00"
      }
    ],
    "Memorias-Disco-WIFI": [
      {
        "item": 77,
        "codigo": null,
        "denominacion": "Memoria 4GB DDR3L",
        "unidad": "Unidad",
        "coeficiente": 1.35,
        "costo_fob": 15.0,
        "costo_fabrica": 20.25,
        "fecha": "2025-10-30 00:00:00"
      },
      {
        "item": 78,
        "codigo": null,
        "denominacion": "Memoria 8GB DDR3",
        "unidad": "Unidad",
        "coeficiente": 1.35,
        "costo_fob": 40.0,
        "costo_fabrica": 54.0,
        "fecha": "2025-10-30 00:00:00"
      },
      {
        "item": 79,
        "codigo": null,
        "denominacion": "Memoria 4GB DRR4",
        "unidad": "Unidad",
        "coeficiente": 1.35,
        "costo_fob": 42.0,
        "costo_fabrica": 56.7,
        "fecha": "2025-10-30 00:00:00"
      },
      {
        "item": 80,
        "codigo": null,
        "denominacion": "Disco 64GB mSata",
        "unidad": "Unidad",
        "coeficiente": 1.35,
        "costo_fob": 28.36,
        "costo_fabrica": 38.286,
        "fecha": "2025-10-30 00:00:00"
      },
      {
        "item": 81,
        "codigo": null,
        "denominacion": "Disco 120GB mSata",
        "unidad": "Unidad",
        "coeficiente": 1.35,
        "costo_fob": 36.79,
        "costo_fabrica": 49.6665,
        "fecha": "2025-10-30 00:00:00"
      },
      {
        "item": 82,
        "codigo": null,
        "denominacion": "Disco 256GB mSata",
        "unidad": "Unidad",
        "coeficiente": 1.35,
        "costo_fob": 59.65,
        "costo_fabrica": 80.5275,
        "fecha": "2025-10-30 00:00:00"
      },
      {
        "item": 83,
        "codigo": null,
        "denominacion": "Modulo WIFI",
        "unidad": "Unidad",
        "coeficiente": 1.35,
        "costo_fob": 20.0,
        "costo_fabrica": 27.0,
        "fecha": "2025-10-30 00:00:00"
      },
      {
        "item": 84,
        "codigo": null,
        "denominacion": "DISCO SSD msata 480",
        "unidad": "Unidad",
        "coeficiente": 1.0,
        "costo_fob": 182.0,
        "costo_fabrica": 182.0,
        "fecha": "2025-10-30 00:00:00"
      },
      {
        "item": 85,
        "codigo": null,
        "denominacion": "microSD 32G",
        "unidad": "Unidad",
        "coeficiente": 1.0,
        "costo_fob": 12.0,
        "costo_fabrica": 12.0,
        "fecha": "2025-10-30 00:00:00"
      },
      {
        "item": 86,
        "codigo": null,
        "denominacion": "Pendrive USB 32Gb",
        "unidad": "Unidad",
        "coeficiente": 1.0,
        "costo_fob": 12.0,
        "costo_fabrica": 12.0,
        "fecha": "2025-10-30 00:00:00"
      }
    ],
    "All In One StarVisual": [
      {
        "item": 87,
        "codigo": null,
        "denominacion": "21.5\" Touch  i5 8Gb 128Gb WiFi Win",
        "unidad": "Unidad",
        "coeficiente": 1.8,
        "costo_fob": 313.0,
        "costo_fabrica": 563.4,
        "fecha": "2025-10-30 00:00:00"
      },
      {
        "item": 88,
        "codigo": null,
        "denominacion": "21.5\" Touch Android rk 3568 2Gb 16Gb",
        "unidad": "Unidad",
        "coeficiente": 1.8,
        "costo_fob": 201.0,
        "costo_fabrica": 361.8,
        "fecha": "2025-10-30 00:00:00"
      },
      {
        "item": 89,
        "codigo": null,
        "denominacion": "43\" Touch i5 4Gb 128Gb WiFi Win",
        "unidad": "Unidad",
        "coeficiente": 1.8,
        "costo_fob": 547.0,
        "costo_fabrica": 984.6,
        "fecha": "2025-10-30 00:00:00"
      },
      {
        "item": 90,
        "codigo": null,
        "denominacion": "43\" Touch Android rk 3568 2Gb 16Gb",
        "unidad": "Unidad",
        "coeficiente": 1.8,
        "costo_fob": 442.0,
        "costo_fabrica": 795.6,
        "fecha": "2025-10-30 00:00:00"
      },
      {
        "item": 91,
        "codigo": null,
        "denominacion": "55\" No Touch i5 128Gb Wifi 4Gb Win",
        "unidad": "Unidad",
        "coeficiente": 1.8,
        "costo_fob": 663.0,
        "costo_fabrica": 1193.4,
        "fecha": "2025-10-30 00:00:00"
      },
      {
        "item": 92,
        "codigo": null,
        "denominacion": "21.5-inch All-in-One touch screen, Windows 10, Intel® Celeron® BayTrail J1900 Quad Core (2M cache, 1.99 GHz) with 4GB RAM and 64GB SSD",
        "unidad": "Unidad",
        "coeficiente": 1.8,
        "costo_fob": 243.0,
        "costo_fabrica": 437.40000000000003,
        "fecha": "2025-10-30 00:00:00"
      },
      {
        "item": 93,
        "codigo": null,
        "denominacion": "10\" Touch rasberry pi",
        "unidad": "Unidad",
        "coeficiente": 1.8,
        "costo_fob": 228.0,
        "costo_fabrica": 410.40000000000003,
        "fecha": "2025-10-30 00:00:00"
      },
      {
        "item": 94,
        "codigo": null,
        "denominacion": "10\" Touch Celeron J1900 4Gb 128Gb WiFi Win",
        "unidad": "Unidad",
        "coeficiente": 1.8,
        "costo_fob": 202.0,
        "costo_fabrica": 363.6,
        "fecha": "2025-10-30 00:00:00"
      }
    ],
    "Totem StarVisual": [
      {
        "item": 95,
        "codigo": null,
        "denominacion": "32\" Indoor floor standing kiosc Android",
        "unidad": "Unidad",
        "coeficiente": 1.8,
        "costo_fob": 378.0,
        "costo_fabrica": 680.4,
        "fecha": "2025-10-30 00:00:00"
      },
      {
        "item": 96,
        "codigo": null,
        "denominacion": "43\" Indoor floor standing kiosc Android",
        "unidad": "Unidad",
        "coeficiente": 1.8,
        "costo_fob": 458.0,
        "costo_fabrica": 824.4,
        "fecha": "2025-10-30 00:00:00"
      },
      {
        "item": 97,
        "codigo": null,
        "denominacion": "55\" Indoor floor standing kiosc Android",
        "unidad": "Unidad",
        "coeficiente": 1.8,
        "costo_fob": 583.0,
        "costo_fabrica": 1049.4,
        "fecha": "2025-10-30 00:00:00"
      },
      {
        "item": 98,
        "codigo": null,
        "denominacion": "32\" Outdoor floor standing kiosc Android",
        "unidad": "Unidad",
        "coeficiente": 1.8,
        "costo_fob": 1032.0,
        "costo_fabrica": 1857.6000000000001,
        "fecha": "2025-10-30 00:00:00"
      },
      {
        "item": 99,
        "codigo": null,
        "denominacion": "43\" Outdoor floor standing kiosc Android",
        "unidad": "Unidad",
        "coeficiente": 1.8,
        "costo_fob": 1141.0,
        "costo_fabrica": 2053.8,
        "fecha": "2025-10-30 00:00:00"
      },
      {
        "item": 100,
        "codigo": null,
        "denominacion": "55\" Outdoor floor standing kiosc Android",
        "unidad": "Unidad",
        "coeficiente": 1.8,
        "costo_fob": 1529.0,
        "costo_fabrica": 2752.2000000000003,
        "fecha": "2025-10-30 00:00:00"
      }
    ],
    "Impresoras": [
      {
        "item": 101,
        "codigo": "NP-F2092D",
        "denominacion": "NP2092 (60mm)",
        "unidad": "Unidad",
        "coeficiente": 1.35,
        "costo_fob": 159.0,
        "costo_fabrica": 214.65,
        "fecha": "2025-10-30 00:00:00"
      },
      {
        "item": 102,
        "codigo": "NP-3611BD-3",
        "denominacion": "NP3611 (80mm)",
        "unidad": "Unidad",
        "coeficiente": 1.35,
        "costo_fob": 249.0,
        "costo_fabrica": 336.15000000000003,
        "fecha": "2025-10-30 00:00:00"
      },
      {
        "item": 103,
        "codigo": "BEZ-230",
        "denominacion": "Bezels (Presenters NP2092)",
        "unidad": "Unidad",
        "coeficiente": 1.35,
        "costo_fob": 24.0,
        "costo_fabrica": 32.400000000000006,
        "fecha": "2025-10-30 00:00:00"
      },
      {
        "item": 104,
        "codigo": "BEZ-420",
        "denominacion": "Bezels (Presenters NP3611)",
        "unidad": "Unidad",
        "coeficiente": 1.35,
        "costo_fob": 36.0,
        "costo_fabrica": 48.6,
        "fecha": "2025-10-30 00:00:00"
      },
      {
        "item": 105,
        "codigo": "80mm RS232+USB+LAN",
        "denominacion": "Cashino KP-300H",
        "unidad": "Unidad",
        "coeficiente": 1.35,
        "costo_fob": 115.0,
        "costo_fabrica": 155.25,
        "fecha": "2025-10-30 00:00:00"
      },
      {
        "item": 106,
        "codigo": "60mm RS232+USB+LAN",
        "denominacion": "Custom TG2460H",
        "unidad": "Unidad",
        "coeficiente": 1.35,
        "costo_fob": 450.0,
        "costo_fabrica": 607.5,
        "fecha": "2025-10-30 00:00:00"
      },
      {
        "item": 107,
        "codigo": "(80mm con presenter)",
        "denominacion": "Custom VKP80II",
        "unidad": "Unidad",
        "coeficiente": 1.35,
        "costo_fob": 800.0,
        "costo_fabrica": 1080.0,
        "fecha": "2025-10-30 00:00:00"
      },
      {
        "item": 108,
        "codigo": "Impresora Etiquetas",
        "denominacion": "Impresora Brother QL-800",
        "unidad": "Unidad",
        "coeficiente": 1.0,
        "costo_fob": 448.0,
        "costo_fabrica": 448.0,
        "fecha": null
      }
    ],
    "Lectores": [
      {
        "item": 109,
        "codigo": null,
        "denominacion": "LV3000-H",
        "unidad": "Unidad",
        "coeficiente": 1.35,
        "costo_fob": 98.0,
        "costo_fabrica": 132.3,
        "fecha": "2025-10-30 00:00:00"
      },
      {
        "item": 110,
        "codigo": null,
        "denominacion": "Huella",
        "unidad": "Unidad",
        "coeficiente": 1.35,
        "costo_fob": 250.0,
        "costo_fabrica": 337.5,
        "fecha": "2025-10-30 00:00:00"
      },
      {
        "item": 111,
        "codigo": null,
        "denominacion": "LECTOR Chip y contacless + lector HID wirgand",
        "unidad": "Unidad",
        "coeficiente": 1.35,
        "costo_fob": 390.0,
        "costo_fabrica": 526.5,
        "fecha": "2025-10-30 00:00:00"
      },
      {
        "item": 112,
        "codigo": null,
        "denominacion": "Lector 1D/2D blanco",
        "unidad": "Unidad",
        "coeficiente": 1.35,
        "costo_fob": 75.0,
        "costo_fabrica": 101.25,
        "fecha": "2025-10-30 00:00:00"
      },
      {
        "item": 113,
        "codigo": null,
        "denominacion": "Lector de Pasaporte MRZ",
        "unidad": "Unidad",
        "coeficiente": 1.0,
        "costo_fob": 400.0,
        "costo_fabrica": 400.0,
        "fecha": "2025-10-30 00:00:00"
      },
      {
        "item": 114,
        "codigo": "Alibaba",
        "denominacion": "Biomini Suprema 2",
        "unidad": "Unidad",
        "coeficiente": 1.35,
        "costo_fob": 116.5,
        "costo_fabrica": 157.275,
        "fecha": "2025-10-30 00:00:00"
      },
      {
        "item": 115,
        "codigo": "lectora RFID barcodes inc",
        "denominacion": "Lectora Omnikey 5427",
        "unidad": "Unidad",
        "coeficiente": 1.35,
        "costo_fob": 124.0,
        "costo_fabrica": 167.4,
        "fecha": "2025-10-30 00:00:00"
      }
    ],
    "Sensores": [
      {
        "item": 116,
        "codigo": "PESI-T12NO3MD",
        "denominacion": "Emisor-Receptor",
        "unidad": "Unidad",
        "coeficiente": 1.35,
        "costo_fob": 11.7,
        "costo_fabrica": 15.795,
        "fecha": "2025-10-30 00:00:00"
      },
      {
        "item": 117,
        "codigo": "IPS-12NC4B",
        "denominacion": "Inductivo",
        "unidad": "Unidad",
        "coeficiente": 1.35,
        "costo_fob": 10.0,
        "costo_fabrica": 13.5,
        "fecha": "2025-10-30 00:00:00"
      },
      {
        "item": 118,
        "codigo": "PES-D18NO50D",
        "denominacion": "Capacitivo (PET)",
        "unidad": "Unidad",
        "coeficiente": 1.0,
        "costo_fob": 100.0,
        "costo_fabrica": 100.0,
        "fecha": "2025-10-30 00:00:00"
      },
      {
        "item": 119,
        "codigo": null,
        "denominacion": "Reflectivo",
        "unidad": "Unidad",
        "coeficiente": 1.35,
        "costo_fob": 11.7,
        "costo_fabrica": 15.795,
        "fecha": "2025-10-30 00:00:00"
      },
      {
        "item": 120,
        "codigo": null,
        "denominacion": "Reflectivo Banner",
        "unidad": "Unidad",
        "coeficiente": 1.35,
        "costo_fob": 90.0,
        "costo_fabrica": 121.50000000000001,
        "fecha": "2025-10-30 00:00:00"
      }
    ],
    "Motores": [
      {
        "item": 121,
        "codigo": "Z4D60-24GN-30S/4GN30K",
        "denominacion": "Motor con reductor Z4D60-24GN-30S/4GN30K",
        "unidad": "Unidad",
        "coeficiente": 1.35,
        "costo_fob": 46.23,
        "costo_fabrica": 62.4105,
        "fecha": "2025-10-30 00:00:00"
      },
      {
        "item": 122,
        "codigo": null,
        "denominacion": "Motoreductor Ancora",
        "unidad": "Unidad",
        "coeficiente": 1.0,
        "costo_fob": 63.0,
        "costo_fabrica": 63.0,
        "fecha": "2025-10-30 00:00:00"
      },
      {
        "item": 123,
        "codigo": null,
        "denominacion": "Motor con reductor triturador 220V 3/4 HP",
        "unidad": "Unidad",
        "coeficiente": 1.0,
        "costo_fob": 950.0,
        "costo_fabrica": 950.0,
        "fecha": "2025-10-30 00:00:00"
      },
      {
        "item": 124,
        "codigo": null,
        "denominacion": "Motor con reductor exp. Golosinas",
        "unidad": "Unidad",
        "coeficiente": 1.0,
        "costo_fob": 63.0,
        "costo_fabrica": 63.0,
        "fecha": "2025-10-30 00:00:00"
      }
    ],
    "Placas DCM": [
      {
        "item": 125,
        "codigo": null,
        "denominacion": "DCM010 (MUFFIN PWR)",
        "unidad": "Unidad",
        "coeficiente": 1.0,
        "costo_fob": 38.94,
        "costo_fabrica": 38.94,
        "fecha": "2025-10-30 00:00:00"
      },
      {
        "item": 126,
        "codigo": null,
        "denominacion": "DCM011 (MUFFIN CONTROL)",
        "unidad": "Unidad",
        "coeficiente": 1.0,
        "costo_fob": 70.42,
        "costo_fabrica": 70.42,
        "fecha": "2025-10-30 00:00:00"
      },
      {
        "item": 127,
        "codigo": null,
        "denominacion": "DCM012 (MUFFIN PANEL)",
        "unidad": "Unidad",
        "coeficiente": 1.0,
        "costo_fob": 59.83,
        "costo_fabrica": 59.83,
        "fecha": "2025-10-30 00:00:00"
      },
      {
        "item": 128,
        "codigo": null,
        "denominacion": "DCM821D (PICTOGRAMA Leds)",
        "unidad": "Unidad",
        "coeficiente": 1.0,
        "costo_fob": 56.01,
        "costo_fabrica": 56.01,
        "fecha": "2025-10-30 00:00:00"
      },
      {
        "item": 129,
        "codigo": null,
        "denominacion": "DCM834E (CORE)",
        "unidad": "Unidad",
        "coeficiente": 1.0,
        "costo_fob": 37.86,
        "costo_fabrica": 37.86,
        "fecha": "2025-10-30 00:00:00"
      },
      {
        "item": 130,
        "codigo": null,
        "denominacion": "DCM840D (PCA200 sin Core)",
        "unidad": "Unidad",
        "coeficiente": 1.0,
        "costo_fob": 59.97,
        "costo_fabrica": 59.97,
        "fecha": "2025-10-30 00:00:00"
      },
      {
        "item": 131,
        "codigo": null,
        "denominacion": "DCM851B (PCA350 sin Core)",
        "unidad": "Unidad",
        "coeficiente": 1.0,
        "costo_fob": 90.93,
        "costo_fabrica": 90.93,
        "fecha": "2025-10-30 00:00:00"
      },
      {
        "item": 132,
        "codigo": null,
        "denominacion": "DCM860C (PCM100)",
        "unidad": "Unidad",
        "coeficiente": 1.0,
        "costo_fob": 60.32,
        "costo_fabrica": 60.32,
        "fecha": "2025-10-30 00:00:00"
      },
      {
        "item": 133,
        "codigo": "Controladora motor",
        "denominacion": "DCM861C (PCM150)",
        "unidad": "Unidad",
        "coeficiente": 1.0,
        "costo_fob": 72.7,
        "costo_fabrica": 72.7,
        "fecha": "2025-10-30 00:00:00"
      },
      {
        "item": 134,
        "codigo": null,
        "denominacion": "DCM829B (PCA100)",
        "unidad": "Unidad",
        "coeficiente": 1.0,
        "costo_fob": 51.79,
        "costo_fabrica": 51.79,
        "fecha": "2025-10-30 00:00:00"
      },
      {
        "item": 135,
        "codigo": null,
        "denominacion": "DCM870B (PCA150)",
        "unidad": "Unidad",
        "coeficiente": 1.0,
        "costo_fob": 73.87,
        "costo_fabrica": 73.87,
        "fecha": "2025-10-30 00:00:00"
      },
      {
        "item": 136,
        "codigo": null,
        "denominacion": "DCM4027C (BUZON)",
        "unidad": "Unidad",
        "coeficiente": 1.0,
        "costo_fob": 58.29,
        "costo_fabrica": 58.29,
        "fecha": "2025-10-30 00:00:00"
      },
      {
        "item": 137,
        "codigo": "Placa esclava AG",
        "denominacion": "DCM4031B (esclavo AG)",
        "unidad": "Unidad",
        "coeficiente": 1.0,
        "costo_fob": 46.0,
        "costo_fabrica": 46.0,
        "fecha": "2025-10-30 00:00:00"
      },
      {
        "item": 138,
        "codigo": null,
        "denominacion": "DCM846 (consola)",
        "unidad": "Unidad",
        "coeficiente": 1.0,
        "costo_fob": 10.0,
        "costo_fabrica": 10.0,
        "fecha": "2025-10-30 00:00:00"
      },
      {
        "item": 139,
        "codigo": "Interfase matriz pictograma",
        "denominacion": "DCM4041 (PMX100)",
        "unidad": "Unidad",
        "coeficiente": 1.0,
        "costo_fob": 30.0,
        "costo_fabrica": 30.0,
        "fecha": "2025-10-30 00:00:00"
      },
      {
        "item": 140,
        "codigo": null,
        "denominacion": "DCM8101 (semaforo Red&GREEN)",
        "unidad": "Unidad",
        "coeficiente": 1.0,
        "costo_fob": 10.0,
        "costo_fabrica": 10.0,
        "fecha": "2025-10-30 00:00:00"
      },
      {
        "item": 141,
        "codigo": null,
        "denominacion": "Encoder",
        "unidad": "Unidad",
        "coeficiente": 1.0,
        "costo_fob": 10.0,
        "costo_fabrica": 10.0,
        "fecha": "2025-10-30 00:00:00"
      }
    ],
    "Fuentes": [
      {
        "item": 142,
        "codigo": null,
        "denominacion": "Fuentes 5 Vdc 3A",
        "unidad": "Unidad",
        "coeficiente": 1.0,
        "costo_fob": 16.0,
        "costo_fabrica": 16.0,
        "fecha": "2025-10-30 00:00:00"
      },
      {
        "item": 143,
        "codigo": null,
        "denominacion": "Fuentes 5 Vdc 5A",
        "unidad": "Unidad",
        "coeficiente": 1.0,
        "costo_fob": 16.0,
        "costo_fabrica": 16.0,
        "fecha": "2025-10-30 00:00:00"
      },
      {
        "item": 144,
        "codigo": null,
        "denominacion": "Fuentes 12 Vdc 5A  (60 W)",
        "unidad": "Unidad",
        "coeficiente": 1.0,
        "costo_fob": 16.0,
        "costo_fabrica": 16.0,
        "fecha": "2025-10-30 00:00:00"
      },
      {
        "item": 145,
        "codigo": null,
        "denominacion": "Fuentes 12 Vdc 10A",
        "unidad": "Unidad",
        "coeficiente": 1.0,
        "costo_fob": 32.0,
        "costo_fabrica": 32.0,
        "fecha": "2025-10-30 00:00:00"
      },
      {
        "item": 146,
        "codigo": null,
        "denominacion": "Fuentes 24 Vdc",
        "unidad": "Unidad",
        "coeficiente": 1.0,
        "costo_fob": 16.0,
        "costo_fabrica": 16.0,
        "fecha": "2025-10-30 00:00:00"
      },
      {
        "item": 147,
        "codigo": null,
        "denominacion": "Fuentes 24 Vdc especial",
        "unidad": "Unidad",
        "coeficiente": 1.0,
        "costo_fob": 47.0,
        "costo_fabrica": 47.0,
        "fecha": "2025-10-30 00:00:00"
      },
      {
        "item": 148,
        "codigo": null,
        "denominacion": "Fuentes 12Vdc especial",
        "unidad": "Unidad",
        "coeficiente": 1.0,
        "costo_fob": 47.0,
        "costo_fabrica": 47.0,
        "fecha": "2025-10-30 00:00:00"
      },
      {
        "item": 149,
        "codigo": null,
        "denominacion": "Trafo 12VAC 5A",
        "unidad": "Unidad",
        "coeficiente": 1.0,
        "costo_fob": 10.0,
        "costo_fabrica": 10.0,
        "fecha": "2025-10-30 00:00:00"
      },
      {
        "item": 150,
        "codigo": null,
        "denominacion": "UPS 500VA",
        "unidad": "Unidad",
        "coeficiente": 1.0,
        "costo_fob": 70.0,
        "costo_fabrica": 70.0,
        "fecha": "2025-10-30 00:00:00"
      }
    ],
    "Sistema Operativo": [
      {
        "item": 151,
        "codigo": null,
        "denominacion": "Sistema Operativo Win 7 Starter",
        "unidad": "Unidad",
        "coeficiente": 1.0,
        "costo_fob": 120.0,
        "costo_fabrica": 120.0,
        "fecha": "2025-10-30 00:00:00"
      },
      {
        "item": 152,
        "codigo": null,
        "denominacion": "SO Win 10 IoT celeron",
        "unidad": "Unidad",
        "coeficiente": 1.0,
        "costo_fob": 110.0,
        "costo_fabrica": 110.0,
        "fecha": "2025-10-30 00:00:00"
      },
      {
        "item": 153,
        "codigo": null,
        "denominacion": "SO Win 10 IoT i3",
        "unidad": "Unidad",
        "coeficiente": 1.0,
        "costo_fob": 140.0,
        "costo_fabrica": 140.0,
        "fecha": "2025-10-30 00:00:00"
      },
      {
        "item": 154,
        "codigo": null,
        "denominacion": "SO Win 10 IoT i7",
        "unidad": "Unidad",
        "coeficiente": 1.0,
        "costo_fob": 180.0,
        "costo_fabrica": 180.0,
        "fecha": "2025-10-30 00:00:00"
      },
      {
        "item": 155,
        "codigo": null,
        "denominacion": "SO Win 10 Pro",
        "unidad": "Unidad",
        "coeficiente": 1.0,
        "costo_fob": 220.0,
        "costo_fabrica": 220.0,
        "fecha": "2025-10-30 00:00:00"
      },
      {
        "item": 156,
        "codigo": null,
        "denominacion": "SO Win 11 Pro",
        "unidad": "Unidad",
        "coeficiente": 1.0,
        "costo_fob": 220.0,
        "costo_fabrica": 220.0,
        "fecha": "2025-10-30 00:00:00"
      }
    ],
    "Varios": [
      {
        "item": 157,
        "codigo": null,
        "denominacion": "Matriz de LED",
        "unidad": "Unidad",
        "coeficiente": 1.35,
        "costo_fob": 10.0,
        "costo_fabrica": 13.5,
        "fecha": "2025-10-30 00:00:00"
      },
      {
        "item": 158,
        "codigo": null,
        "denominacion": "Termometro M3",
        "unidad": "Unidad",
        "coeficiente": 1.35,
        "costo_fob": 27.0,
        "costo_fabrica": 36.45,
        "fecha": "2025-10-30 00:00:00"
      },
      {
        "item": 159,
        "codigo": "KMY299H",
        "denominacion": "Teclado Industrial",
        "unidad": "Unidad",
        "coeficiente": 1.35,
        "costo_fob": 131.0,
        "costo_fabrica": 176.85000000000002,
        "fecha": "2025-10-30 00:00:00"
      },
      {
        "item": 160,
        "codigo": "KR-566N",
        "denominacion": "Cerradura Electrónica",
        "unidad": "Unidad",
        "coeficiente": 1.35,
        "costo_fob": 7.5,
        "costo_fabrica": 10.125,
        "fecha": "2025-10-30 00:00:00"
      },
      {
        "item": 161,
        "codigo": "KR-CU",
        "denominacion": "Lock Control Board KR-CU - TODOS",
        "unidad": "Unidad",
        "coeficiente": 1.35,
        "costo_fob": 63.0,
        "costo_fabrica": 85.05000000000001,
        "fecha": "2025-10-30 00:00:00"
      },
      {
        "item": 162,
        "codigo": "KR-BU",
        "denominacion": "Lock Control Board c/0.5m net cable) KR-BU - MAESTRO",
        "unidad": "Unidad",
        "coeficiente": 1.35,
        "costo_fob": 63.0,
        "costo_fabrica": 85.05000000000001,
        "fecha": "2025-10-30 00:00:00"
      },
      {
        "item": 163,
        "codigo": "Simple, sin capuchón",
        "denominacion": "Conector Externo USB",
        "unidad": "Unidad",
        "coeficiente": 1.35,
        "costo_fob": 10.0,
        "costo_fabrica": 13.5,
        "fecha": "2025-10-30 00:00:00"
      },
      {
        "item": 164,
        "codigo": "Simple, sin capuchón",
        "denominacion": "Conector Externo RJ45",
        "unidad": "Unidad",
        "coeficiente": 1.35,
        "costo_fob": 10.0,
        "costo_fabrica": 13.5,
        "fecha": "2025-10-30 00:00:00"
      },
      {
        "item": 165,
        "codigo": "buzón de ropa",
        "denominacion": "Cerradura electromagnética",
        "unidad": "Unidad",
        "coeficiente": 1.35,
        "costo_fob": null,
        "costo_fabrica": 0.0,
        "fecha": "2025-10-30 00:00:00"
      },
      {
        "item": 166,
        "codigo": "ACT-IR220LPlus Actisys",
        "denominacion": "Adaptador IRDA-RS232",
        "unidad": "Unidad",
        "coeficiente": 1.35,
        "costo_fob": 116.5,
        "costo_fabrica": 157.275,
        "fecha": "2025-10-30 00:00:00"
      },
      {
        "item": 167,
        "codigo": "Matriz + Placa interfase",
        "denominacion": "Pictograma viejo nivel",
        "unidad": "Unidad",
        "coeficiente": 1.0,
        "costo_fob": 45.0,
        "costo_fabrica": 45.0,
        "fecha": "2025-10-30 00:00:00"
      },
      {
        "item": 168,
        "codigo": "tira de leds",
        "denominacion": "Semáforo simple",
        "unidad": "Unidad",
        "coeficiente": 1.0,
        "costo_fob": 20.0,
        "costo_fabrica": 20.0,
        "fecha": "2025-10-30 00:00:00"
      },
      {
        "item": 169,
        "codigo": "matriz de leds + placa interfase",
        "denominacion": "Semáforo matricial",
        "unidad": "Unidad",
        "coeficiente": 1.0,
        "costo_fob": 60.0,
        "costo_fabrica": 60.0,
        "fecha": "2025-10-30 00:00:00"
      },
      {
        "item": 170,
        "codigo": "65 kg",
        "denominacion": "Retentor 65Kg",
        "unidad": "Unidad",
        "coeficiente": 1.0,
        "costo_fob": 75.0,
        "costo_fabrica": 75.0,
        "fecha": "2025-10-30 00:00:00"
      },
      {
        "item": 171,
        "codigo": "9101-H",
        "denominacion": "Solenoide",
        "unidad": "Unidad",
        "coeficiente": 1.0,
        "costo_fob": 38.0,
        "costo_fabrica": 38.0,
        "fecha": "2025-10-30 00:00:00"
      },
      {
        "item": 172,
        "codigo": "PRLR C",
        "denominacion": "Microswitch chico (MC)",
        "unidad": "Unidad",
        "coeficiente": 1.0,
        "costo_fob": 6.0,
        "costo_fabrica": 6.0,
        "fecha": "2025-10-30 00:00:00"
      },
      {
        "item": 173,
        "codigo": "MPR 2L",
        "denominacion": "Microswitch grande (MS)",
        "unidad": "Unidad",
        "coeficiente": 1.0,
        "costo_fob": 6.5,
        "costo_fabrica": 6.5,
        "fecha": "2025-10-30 00:00:00"
      },
      {
        "item": 174,
        "codigo": null,
        "denominacion": "Pictograma nuevo",
        "unidad": "Unidad",
        "coeficiente": 1.0,
        "costo_fob": 5.0,
        "costo_fabrica": 5.0,
        "fecha": "2025-10-30 00:00:00"
      },
      {
        "item": 175,
        "codigo": null,
        "denominacion": "Sensores de Presencia de Lockers",
        "unidad": "Unidad",
        "coeficiente": 1.35,
        "costo_fob": 16.0,
        "costo_fabrica": 21.6,
        "fecha": "2025-10-30 00:00:00"
      }
    ],
    "Mecatronica Importada": [
      {
        "item": 176,
        "codigo": null,
        "denominacion": "Mecanismo Molinete MC Low cost",
        "unidad": "Unidad",
        "coeficiente": 1.8,
        "costo_fob": 75.0,
        "costo_fabrica": 135.0,
        "fecha": "2025-10-30 00:00:00"
      },
      {
        "item": 177,
        "codigo": "Servo Motor with Gear Box",
        "denominacion": "Mecanismo AG (motor)",
        "unidad": "Unidad",
        "coeficiente": 1.8,
        "costo_fob": 75.0,
        "costo_fabrica": 135.0,
        "fecha": "2025-10-30 00:00:00"
      },
      {
        "item": 178,
        "codigo": "MBC200",
        "denominacion": "Placa AG 1 MBC200",
        "unidad": "Unidad",
        "coeficiente": 1.8,
        "costo_fob": 57.0,
        "costo_fabrica": 102.60000000000001,
        "fecha": "2025-10-30 00:00:00"
      },
      {
        "item": 179,
        "codigo": null,
        "denominacion": "Placa AG 2",
        "unidad": "Unidad",
        "coeficiente": 1.8,
        "costo_fob": null,
        "costo_fabrica": 0.0,
        "fecha": "2025-10-30 00:00:00"
      },
      {
        "item": 180,
        "codigo": null,
        "denominacion": "Mecanismo barrera",
        "unidad": "Unidad",
        "coeficiente": 1.8,
        "costo_fob": null,
        "costo_fabrica": 0.0,
        "fecha": "2025-10-30 00:00:00"
      }
    ]
  },
  "Componentes Electricos y armado final": {
    "Componentes Electricos": [
      {
        "item": 181,
        "codigo": null,
        "denominacion": "Disyuntor",
        "unidad": "Unidad",
        "coeficiente": 1.0,
        "costo_fob": 40.0,
        "costo_fabrica": 40.0,
        "fecha": "2025-10-30 00:00:00"
      },
      {
        "item": 182,
        "codigo": null,
        "denominacion": "Llave térmica de 16A",
        "unidad": "Unidad",
        "coeficiente": 1.0,
        "costo_fob": 10.0,
        "costo_fabrica": 10.0,
        "fecha": "2025-10-30 00:00:00"
      },
      {
        "item": 183,
        "codigo": null,
        "denominacion": "Caja porta térmica",
        "unidad": "Unidad",
        "coeficiente": 1.0,
        "costo_fob": 2.0,
        "costo_fabrica": 2.0,
        "fecha": "2025-10-30 00:00:00"
      },
      {
        "item": 184,
        "codigo": null,
        "denominacion": "Contactor",
        "unidad": "Unidad",
        "coeficiente": 1.0,
        "costo_fob": 30.0,
        "costo_fabrica": 30.0,
        "fecha": "2025-10-30 00:00:00"
      },
      {
        "item": 185,
        "codigo": null,
        "denominacion": "Bloque aux contactor",
        "unidad": "Unidad",
        "coeficiente": 1.0,
        "costo_fob": 20.0,
        "costo_fabrica": 20.0,
        "fecha": "2025-10-30 00:00:00"
      },
      {
        "item": 186,
        "codigo": null,
        "denominacion": "Borneras",
        "unidad": "Unidad",
        "coeficiente": 1.0,
        "costo_fob": 2.0,
        "costo_fabrica": 2.0,
        "fecha": "2025-10-30 00:00:00"
      },
      {
        "item": 187,
        "codigo": null,
        "denominacion": "Parlantes",
        "unidad": "Unidad",
        "coeficiente": 1.0,
        "costo_fob": 8.0,
        "costo_fabrica": 8.0,
        "fecha": "2025-10-30 00:00:00"
      },
      {
        "item": 188,
        "codigo": null,
        "denominacion": "Ventiladores",
        "unidad": "Unidad",
        "coeficiente": 1.0,
        "costo_fob": 5.0,
        "costo_fabrica": 5.0,
        "fecha": "2025-10-30 00:00:00"
      },
      {
        "item": 189,
        "codigo": null,
        "denominacion": "Zapatilla",
        "unidad": "Unidad",
        "coeficiente": 1.0,
        "costo_fob": 5.0,
        "costo_fabrica": 5.0,
        "fecha": "2025-10-30 00:00:00"
      },
      {
        "item": 190,
        "codigo": null,
        "denominacion": "Manojo de cables",
        "unidad": "Unidad",
        "coeficiente": 1.0,
        "costo_fob": 70.0,
        "costo_fabrica": 70.0,
        "fecha": "2025-10-30 00:00:00"
      },
      {
        "item": 191,
        "codigo": null,
        "denominacion": "Cámara Webcam",
        "unidad": "Unidad",
        "coeficiente": 1.0,
        "costo_fob": 24.0,
        "costo_fabrica": 24.0,
        "fecha": "2025-10-30 00:00:00"
      },
      {
        "item": 192,
        "codigo": null,
        "denominacion": "Caja eléctrica (caja, térmica)",
        "unidad": "Unidad",
        "coeficiente": 1.0,
        "costo_fob": 40.0,
        "costo_fabrica": 40.0,
        "fecha": "2025-10-30 00:00:00"
      },
      {
        "item": 193,
        "codigo": null,
        "denominacion": "Disyuntor",
        "unidad": "Unidad",
        "coeficiente": 1.0,
        "costo_fob": 40.0,
        "costo_fabrica": 40.0,
        "fecha": "2025-10-30 00:00:00"
      },
      {
        "item": 194,
        "codigo": null,
        "denominacion": "Repetidor WiFi",
        "unidad": "Unidad",
        "coeficiente": 1.0,
        "costo_fob": 38.0,
        "costo_fabrica": 38.0,
        "fecha": "2025-10-30 00:00:00"
      },
      {
        "item": 195,
        "codigo": null,
        "denominacion": "Modem 4G",
        "unidad": "Unidad",
        "coeficiente": 1.0,
        "costo_fob": 70.0,
        "costo_fabrica": 70.0,
        "fecha": "2025-10-30 00:00:00"
      },
      {
        "item": 196,
        "codigo": null,
        "denominacion": "Micrófono",
        "unidad": "Unidad",
        "coeficiente": 1.0,
        "costo_fob": 10.0,
        "costo_fabrica": 10.0,
        "fecha": "2025-10-30 00:00:00"
      },
      {
        "item": 197,
        "codigo": null,
        "denominacion": "Botón de pánico",
        "unidad": "Unidad",
        "coeficiente": 1.0,
        "costo_fob": 10.0,
        "costo_fabrica": 10.0,
        "fecha": "2025-10-30 00:00:00"
      }
    ],
    "Mano de obra de armado final": [
      {
        "item": 198,
        "codigo": "Materiales y mano de obra promedio",
        "denominacion": "Embalaje de carton",
        "unidad": "Promedio",
        "coeficiente": 1.0,
        "costo_fob": 21.0,
        "costo_fabrica": 21.0,
        "fecha": "2025-10-30 00:00:00"
      },
      {
        "item": 199,
        "codigo": null,
        "denominacion": "Pallet con tratamiento fitosanitario",
        "unidad": "Promedio",
        "coeficiente": 1.0,
        "costo_fob": 20.0,
        "costo_fabrica": 20.0,
        "fecha": "2025-10-30 00:00:00"
      },
      {
        "item": 200,
        "codigo": null,
        "denominacion": "Caja de madera con tratamiento",
        "unidad": "m³",
        "coeficiente": 1.0,
        "costo_fob": 90.0,
        "costo_fabrica": 90.0,
        "fecha": "2025-10-30 00:00:00"
      },
      {
        "item": 201,
        "codigo": null,
        "denominacion": "Armado final",
        "unidad": "Hora",
        "coeficiente": 1.0,
        "costo_fob": 12.0,
        "costo_fabrica": 12.0,
        "fecha": "2025-10-30 00:00:00"
      },
      {
        "item": 202,
        "codigo": null,
        "denominacion": "Test y prueba",
        "unidad": "Hora",
        "coeficiente": 1.0,
        "costo_fob": 12.0,
        "costo_fabrica": 12.0,
        "fecha": "2025-10-30 00:00:00"
      }
    ]
  }
}